{
    "iconUrl": "https://static.wikia.nocookie.net/gensin-impact/images/3/3d/Diluc_Icon.png",
    "name": "Diluc",
    "rarity": "5 Stars",
    "element": "Pyro",
    "weaponType": "Claymore",
    "region": "Mondstadt",
    "elementUrl": "https://static.wikia.nocookie.net/gensin-impact/images/e/e8/Element_Pyro.png",
    "weaponUrl": "https://static.wikia.nocookie.net/gensin-impact/images/5/51/Weapon-class-claymore-icon.png",
    "regionUrl": "https://static.wikia.nocookie.net/gensin-impact/images/c/ce/Mondstadt_Emblem_Night.png",
    "talents": [
        {
            "talentIcon": "https://static.wikia.nocookie.net/gensin-impact/images/5/57/Claymore_Pyro.png",
            "talentName": "Tempered Sword",
            "talentType": "Normal Attack",
            "description": "Normal Attack\nPerforms up to 4 consecutive strikes.\n\nCharged Attack\nDrains Stamina over time to perform continuous slashes.\nAt the end of the sequence, performs a more powerful slash.\n\nPlunging Attack\nPlunges from mid-air to strike the ground, damaging opponents along the path and dealing AoE DMG upon impact.\n",
            "figureUrls": [
                {
                    "url": "https://static.wikia.nocookie.net/gensin-impact/images/d/db/Tempered_Sword_Normal_Preview.gif",
                    "caption": "Normal Attack"
                },
                {
                    "url": "https://static.wikia.nocookie.net/gensin-impact/images/3/30/Tempered_Sword_Charged_Preview.gif",
                    "caption": "Charged Attack"
                },
                {
                    "url": "https://static.wikia.nocookie.net/gensin-impact/images/5/51/Tempered_Sword_Plunging_Preview.gif",
                    "caption": "Plunging Attack"
                }
            ]
        },
        {
            "talentIcon": "https://static.wikia.nocookie.net/gensin-impact/images/5/53/Talent_Searing_Onslaught.png",
            "talentName": "Searing Onslaught",
            "talentType": "Elemental Skill",
            "description": "Performs a forward slash that deals Pyro DMG.\n\nThis skill can be consecutively used 3 times.\nEnters CD if not cast again within a short period.\n",
            "figureUrls": [
                {
                    "url": "https://static.wikia.nocookie.net/gensin-impact/images/a/a8/Searing_Onslaught_Preview.gif",
                    "caption": ""
                },
                {
                    "url": "https://static.wikia.nocookie.net/gensin-impact/images/d/d8/Searing_Onslaught_Preview_Red_Dead_of_Night.gif",
                    "caption": ""
                }
            ]
        },
        {
            "talentIcon": "https://static.wikia.nocookie.net/gensin-impact/images/f/f5/Talent_Dawn.png",
            "talentName": "Dawn",
            "talentType": "Elemental Burst",
            "description": "Releases intense flames to knock back nearby opponents, dealing Pyro DMG.\nThe flames then converge into the weapon, summoning a Phoenix that flies forward and deals massive Pyro DMG to all opponents in its path. The Phoenix explodes upon reaching its destination, causing a large amount of AoE Pyro DMG.\nThe searing flames that run down his blade cause it to be infused with Pyro.\n",
            "figureUrls": [
                {
                    "url": "https://static.wikia.nocookie.net/gensin-impact/images/6/60/Dawn_Preview.gif",
                    "caption": ""
                },
                {
                    "url": "https://static.wikia.nocookie.net/gensin-impact/images/a/a6/Dawn_Preview_Red_Dead_of_Night.gif",
                    "caption": ""
                }
            ]
        },
        {
            "talentIcon": "https://static.wikia.nocookie.net/gensin-impact/images/5/5f/Talent_Relentless.png",
            "talentName": "Relentless",
            "talentType": "1st Ascension Passive",
            "description": "Diluc's Charged Attack Stamina Cost is decreased by 50%, and its duration is increased by 3s.",
            "figureUrls": []
        },
        {
            "talentIcon": "https://static.wikia.nocookie.net/gensin-impact/images/c/c3/Talent_Blessing_of_Phoenix.png",
            "talentName": "Blessing of Phoenix",
            "talentType": "4th Ascension Passive",
            "description": "The Pyro Infusion provided by Dawn lasts for 4s longer. Additionally, Diluc gains 20% Pyro DMG Bonus during the duration of this effect.",
            "figureUrls": []
        },
        {
            "talentIcon": "https://static.wikia.nocookie.net/gensin-impact/images/a/af/Talent_Tradition_of_the_Dawn_Knight.png",
            "talentName": "Tradition of the Dawn Knight",
            "talentType": "Utility Passive",
            "description": "Refunds 15% of the ore used when crafting Claymore-type weapons.",
            "figureUrls": []
        }
    ],
    "constellations": [
        {
            "iconUrl": "https://static.wikia.nocookie.net/gensin-impact/images/7/72/Constellation_Conviction.png",
            "name": "Conviction",
            "level": 1,
            "description": "Diluc deals 15% more DMG to opponents whose HP is above 50%."
        },
        {
            "iconUrl": "https://static.wikia.nocookie.net/gensin-impact/images/b/b4/Constellation_Searing_Ember.png",
            "name": "Searing Ember",
            "level": 2,
            "description": "When Diluc takes DMG, his ATK increases by 10% and his ATK SPD increases by 5%. Lasts for 10s.\nThis effect can stack up to 3 times and can only occur once every 1.5s.\n▼Gameplay Notes▼"
        },
        {
            "iconUrl": "https://static.wikia.nocookie.net/gensin-impact/images/5/52/Constellation_Fire_and_Steel.png",
            "name": "Fire and Steel",
            "level": 3,
            "description": "Increases the Level of Searing Onslaught by 3.\nMaximum upgrade level is 15."
        },
        {
            "iconUrl": "https://static.wikia.nocookie.net/gensin-impact/images/a/a1/Constellation_Flowing_Flame.png",
            "name": "Flowing Flame",
            "level": 4,
            "description": "Casting Searing Onslaught in rhythm greatly increases damage dealt.\n2s after casting Searing Onslaught, casting the next Searing Onslaught in the combo deals 40% additional DMG. This effect lasts for 2s.\n▼Gameplay Notes▼\n▼Preview▼"
        },
        {
            "iconUrl": "https://static.wikia.nocookie.net/gensin-impact/images/d/dc/Constellation_Phoenix%2C_Harbinger_of_Dawn.png",
            "name": "Phoenix, Harbinger of Dawn",
            "level": 5,
            "description": "Increases the Level of Dawn by 3.\nMaximum upgrade level is 15."
        },
        {
            "iconUrl": "https://static.wikia.nocookie.net/gensin-impact/images/1/1c/Constellation_Flaming_Sword%2C_Nemesis_of_the_Dark.png",
            "name": "Flaming Sword, Nemesis of the Dark",
            "level": 6,
            "description": "After casting Searing Onslaught, the next 2 Normal Attacks within the next 6s will have their DMG and ATK SPD increased by 30%.\nAdditionally, Searing Onslaught will not interrupt the Normal Attack combo.\n▼Preview▼"
        }
    ],
    "imageUrls": {
        "card": "https://static.wikia.nocookie.net/gensin-impact/images/e/e7/Diluc_Card.png",
        "wish": "https://static.wikia.nocookie.net/gensin-impact/images/9/91/Character_Diluc_Full_Wish.png",
        "inGame": "https://static.wikia.nocookie.net/gensin-impact/images/d/d4/Character_Diluc_Game.png",
        "nameCard": "https://static.wikia.nocookie.net/gensin-impact/images/c/c7/Item_Diluc_Flames.png"
    }
}