{
  "name": "Hunter's Bow",
  "rarity": 1,
  "attack": 185,
  "subStat": "None",
  "effect": "None",
  "iconUrl": "https://static.wikia.nocookie.net/gensin-impact/images/4/44/Weapon_Hunter%27s_Bow.png",
  "nation": 0,
  "weekdays": 1,
  "materials": [
    {
      "url": "https://static.wikia.nocookie.net/gensin-impact/images/8/84/Item_Mora.png",
      "caption": "Mora"
    },
    {
      "url": "https://static.wikia.nocookie.net/gensin-impact/images/3/33/Item_Boreal_Wolf%27s_Milk_Tooth.png",
      "caption": "Boreal Wolf's Milk Tooth"
    },
    {
      "url": "https://static.wikia.nocookie.net/gensin-impact/images/7/71/Item_Boreal_Wolf%27s_Cracked_Tooth.png",
      "caption": "Boreal Wolf's Cracked Tooth"
    },
    {
      "url": "https://static.wikia.nocookie.net/gensin-impact/images/9/98/Item_Boreal_Wolf%27s_Broken_Fang.png",
      "caption": "Boreal Wolf's Broken Fang"
    },
    {
      "url": "https://static.wikia.nocookie.net/gensin-impact/images/7/77/Item_Dead_Ley_Line_Branch.png",
      "caption": "Dead Ley Line Branch"
    },
    {
      "url": "https://static.wikia.nocookie.net/gensin-impact/images/d/d2/Item_Dead_Ley_Line_Leaves.png",
      "caption": "Dead Ley Line Leaves"
    },
    {
      "url": "https://static.wikia.nocookie.net/gensin-impact/images/c/c9/Item_Treasure_Hoarder_Insignia.png",
      "caption": "Treasure Hoarder Insignia"
    },
    {
      "url": "https://static.wikia.nocookie.net/gensin-impact/images/4/44/Item_Silver_Raven_Insignia.png",
      "caption": "Silver Raven Insignia"
    }
  ],
  "passives": [],
  "images": [
    "https://static.wikia.nocookie.net/gensin-impact/images/4/44/Weapon_Hunter%27s_Bow.png",
    "https://static.wikia.nocookie.net/gensin-impact/images/3/31/Weapon_Hunter%27s_Bow_2nd.png"
  ],
  "ascension": {
    "phases": []
  }
}
